uart_rx.v


module uart_rx (
reset          ,
rxclk          ,
uld_rx_data    ,
rx_data        ,
rx_enable      ,
rx_in          ,
rx_empty
);
// Port declarations
input        reset          ;
input        rxclk          ;
input        uld_rx_data    ;
output [7:0] rx_data        ;
input        rx_enable      ;
input        rx_in          ;
output       rx_empty       ;

// Internal Variables 
reg [7:0]    rx_reg         ;
reg [7:0]    rx_data        ;
reg [3:0]    rx_sample_cnt  ;
reg [3:0]    rx_cnt         ;  
reg          rx_frame_err   ;
reg          rx_over_run    ;
reg          rx_empty       ;
reg          rx_d1          ;
reg          rx_d2          ;
reg          rx_busy        ;

// UART RX Logic
always @ (posedge rxclk or posedge reset)
if (reset) begin
  rx_reg        <= 0; 
  rx_data       <= 0;
  rx_sample_cnt <= 0;
  rx_cnt        <= 0;
  rx_frame_err  <= 0;
  rx_over_run   <= 0;
  rx_empty      <= 1;
  rx_d1         <= 1;
  rx_d2         <= 1;
  rx_busy       <= 0;
end else begin
  // Synchronize the asynch signal
  rx_d1 <= rx_in;
  rx_d2 <= rx_d1;
  // Uload the rx data
  if (uld_rx_data) begin
    rx_data  <= rx_reg;
    rx_empty <= 1;
  end
  // Receive data only when rx is enabled
  if (rx_enable) begin
    // Check if just received start of frame
    if (!rx_busy && !rx_d2) begin
      rx_busy       <= 1;
      rx_sample_cnt <= 1;
      rx_cnt        <= 0;
    end
    // Start of frame detected, Proceed with rest of data
    if (rx_busy) begin
       rx_sample_cnt <= rx_sample_cnt + 1;
       // Logic to sample at middle of data
       if (rx_sample_cnt == 7) begin
          if ((rx_d2 == 1) && (rx_cnt == 0)) begin
            rx_busy <= 0;
          end else begin
            rx_cnt <= rx_cnt + 1; 
            // Start storing the rx data
            if (rx_cnt > 0 && rx_cnt < 9) begin
              rx_reg[rx_cnt - 1] <= rx_d2;
            end
            if (rx_cnt == 9) begin
               rx_busy <= 0;
               // Check if End of frame received correctly
               if (rx_d2 == 0) begin
                 rx_frame_err <= 1;
               end else begin
                 rx_empty     <= 0;
                 rx_frame_err <= 0;
                 // Check if last rx data was not unloaded,
                 rx_over_run  <= (rx_empty) ? 0 : 1;
               end
            end
          end
       end 
    end 
  end
  if (!rx_enable) begin
    rx_busy <= 0;
  end
end

endmodule

uart_tx.v
module uart_tx (
reset          ,
txclk          ,
ld_tx_data     ,
tx_data        ,
tx_enable      ,
tx_out         ,
tx_empty       
);
// Port declarations
input        reset          ;
input        txclk          ;
input        ld_tx_data     ;
input  [7:0] tx_data        ;
input        tx_enable      ;
output       tx_out         ;
output       tx_empty       ;

// Internal Variables 
reg [7:0]    tx_reg         ;
reg          tx_empty       ;
reg          tx_over_run    ;
reg [3:0]    tx_cnt         ;
reg          tx_out         ;
reg [7:0]    rx_reg         ;

// UART TX Logic

always begin @ (posedge txclk or posedge reset)
if (reset) begin
  tx_reg        <= 0;
  tx_empty      <= 1;
  tx_over_run   <= 0;
  tx_out        <= 1;
  tx_cnt        <= 0;
end else begin
   if (ld_tx_data) begin
      if (!tx_empty) begin
        tx_over_run <= 0;
      end else begin
        tx_reg   <= tx_data;
        tx_empty <= 0;
      end
   end
   if (tx_enable && !tx_empty) begin
     if (tx_cnt == 0) begin
       tx_out <= 0;
     end
     if (tx_cnt > 0 && tx_cnt < 9) begin
        tx_out <= tx_reg[tx_cnt -1];
     end
     if (tx_cnt == 9) begin
       tx_out <= 1;
       tx_cnt <= 0;
       tx_empty <= 1;
     end
     tx_cnt <= tx_cnt + 1;

   end
   if (!tx_enable) begin
     tx_cnt <= 0;
   end
end
  end
endmodule

tb.v
module tb();
  integer seedTx = 69; //Seed for Random TX data
  
  integer i;
  integer framesSent=0;
  integer correctFrames = 0;
  
  // Declarations for TX module
  reg txreset;
  reg txclk;
  reg ldtx;
  reg [7:0] tx_data;
  reg tx_en;
  wire tx_out;
  wire tx_empty;
  
  reg [9:0] actualtxout = 0;
  integer tx_index_var;
  integer loop_var;
  
  // Declarations for RX Module
  reg rxreset;
  reg rxclk;
  reg uldrx;
  wire [7:0] rx_data;
  wire rx_en;
  wire rx_in;
  wire rx_empty;
  
  // UART TX instantiation
  uart_tx mytx(
    reset,
    txclk,
    ldtx,
    tx_data,
    tx_en,
    tx_out,
    tx_empty
  );
  
  //UART RX instantiation
  uart_rx myrx(
    rxreset,
    rxclk,
    uldrx,
    rx_data,
    rx_en,
    rx_in,
    rx_empty
  );
  

  //TX Clock
  initial
    txclk=0;
  always begin
    #32 txclk = !txclk;
  end
  
  //RX Clock
  initial rxclk=0;
  always begin
    #2 rxclk = !rxclk;
  end
  
  initial begin
    rxreset = 0;
    txreset = 0;
    ldtx=0;
    
  end


  assign rx_en = tx_en;
  assign rx_in = tx_out;
  
  //Task to send random data using TX module
  task sendTx();
    begin
      tx_en =0;
      txreset =0;
      @(posedge txclk);
      txreset =1; // Reset module
      @(posedge txclk);
      txreset=0;
      @(posedge txclk);
      
      tx_data = $random(seedTx); // Get random data

      @(posedge txclk);
      ldtx=1; // Load into internal registers
      tx_en=1;
      @(posedge txclk);
      ldtx=0;
      
      for (i =0 ;i<9;i= i+1)begin // wait until all 10 bits are transmitted
        @(posedge txclk);
      end
      @(posedge txclk);
      tx_en=0;  // Disable TX
      for(i=0 ;i<7;i=i+1) @(posedge txclk); // Wait for 8 pulses to let RX module catch up
    end
  endtask

  //Task to check if frame sent is sent correctly
  task checkCurrentFrame;
    begin
      framesSent = framesSent + 1;
      if ( actualtxout[0] == 0 && actualtxout[9] == 1 && actualtxout[8:1] == tx_data) // Check for start, stop bits and actual content
        begin
        $display("Transmission check passed for %h",tx_data);
        end
        else 
          begin
          $display("Transmission check failed for %h",tx_data);
          end
        // Check if RX module received data correctly
      if(rx_data == tx_data) 
        begin
        $display("Reception check passed for %h",tx_data);
        end
      else 
        begin
        $display("Reception check failed for %h, received %h",tx_data,rx_data);
        end
      
        if(actualtxout[0] == 0 && actualtxout[9] == 1 && actualtxout[8:1] == tx_data && rx_data == tx_data) // increment correct frame counter
          correctFrames = correctFrames+1;
    end
  endtask
  
  initial begin
    tx_en = 0;
    uldrx=0;
    
    $random(seedTx);
    $dumpfile("dump.vcd"); // for EPWave
  $dumpvars;

    #500
    //Send 20 frames to check
    for(loop_var=0;loop_var<20;loop_var=loop_var+1)begin
      sendTx();#500;
    end
    #500
    $display("CHECKER STATS\nFRAMES SENT = %d, CORRECT FRAMES = %d\n",framesSent,correctFrames);
    $finish;
  end
  always begin
    //Unload data as soon as rx_en is de-asserted
        wait (!rx_empty);
    @(posedge rxclk);
    uldrx = 1;
    @(posedge rxclk);
    uldrx = 0;
    @(posedge rxclk);
  end
  
  always begin
    @(posedge txreset)
    actualtxout =0;
    tx_index_var = 0;
  end
  always begin
    @(posedge tx_en)
    @(negedge tx_out);
    while (tx_en) begin
      //Store tx_out as it is output
      @(posedge txclk);
      actualtxout[tx_index_var] = tx_out;
      tx_index_var = tx_index_var + 1;
    end
    // check each frame as soon as it is sent
    checkCurrentFrame;
  end
endmodule

dump.vcd
$date
    Feb  7, 2024  05:32:14
$end
$version
    TOOL:	xmsim	20.09-s003
$end
$timescale
    1 ns
$end

$scope module tb $end
$var integer  32 !    seedTx $end
$var integer  32 "    i $end
$var integer  32 #    framesSent $end
$var integer  32 $    correctFrames $end
$var reg       1 %    txreset $end
$var reg       1 &    txclk $end
$var reg       1 '    ldtx $end
$var reg       8 (    tx_data [7:0] $end
$var reg       1 )    tx_en $end
$var wire      1 *    tx_out  $end
$var wire      1 +    tx_empty  $end
$var reg      10 ,    actualtxout [9:0] $end
$var integer  32 -    tx_index_var $end
$var integer  32 .    loop_var $end
$var reg       1 /    rxreset $end
$var reg       1 0    rxclk $end
$var reg       1 1    uldrx $end
$var wire      8 2    rx_data [7:0] $end
$var wire      1 3    rx_en  $end
$var wire      1 4    rx_in  $end
$var wire      1 5    rx_empty  $end
$var wire      1 6    reset  $end

$scope module mytx $end
$var wire      1 6    reset  $end
$var wire      1 7    txclk  $end
$var wire      1 8    ld_tx_data  $end
$var wire      8 9    tx_data [7:0] $end
$var wire      1 :    tx_enable  $end
$var reg       1 ;    tx_out $end
$var reg       1 <    tx_empty $end
$var reg       8 =    tx_reg [7:0] $end
$var reg       1 >    tx_over_run $end
$var reg       4 ?    tx_cnt [3:0] $end
$var reg       8 @    rx_reg [7:0] $end
$upscope $end


$scope module myrx $end
$var wire      1 A    reset  $end
$var wire      1 B    rxclk  $end
$var wire      1 C    uld_rx_data  $end
$var reg       8 D    rx_data [7:0] $end
$var wire      1 3    rx_enable  $end
$var wire      1 4    rx_in  $end
$var reg       1 E    rx_empty $end
$var reg       8 F    rx_reg [7:0] $end
$var reg       4 G    rx_sample_cnt [3:0] $end
$var reg       4 H    rx_cnt [3:0] $end
$var reg       1 I    rx_frame_err $end
$var reg       1 J    rx_over_run $end
$var reg       1 K    rx_d1 $end
$var reg       1 L    rx_d2 $end
$var reg       1 M    rx_busy $end
$upscope $end

$upscope $end

$enddefinitions $end
$dumpvars
b10010001011100001000010 !
bx "
b0 #
b0 $
0%
0&
0'
bx (
0)
x*
x+
b0 ,
bx -
bx .
0/
00
01
bx 2
03
x4
x5
z6
07
08
bx 9
0:
x;
x<
bx =
x>
bx ?
bx @
0A
0B
0C
bx D
xE
bx F
bx G
bx H
xI
xJ
xK
xL
xM
$end
#2
10
1B
0M
#4
00
0B
#6
10
1B
#8
00
0B
#10
10
1B
#12
00
0B
#14
10
1B
#16
00
0B
#18
10
1B
#20
00
0B
#22
10
1B
#24
00
0B
#26
10
1B
#28
00
0B
#30
10
1B
#32
1&
00
0B
17
b0 ?
#34
10
1B
#36
00
0B
#38
10
1B
#40
00
0B
#42
10
1B
#44
00
0B
#46
10
1B
#48
00
0B
#50
10
1B
#52
00
0B
#54
10
1B
#56
00
0B
#58
10
1B
#60
00
0B
#62
10
1B
#64
0&
00
0B
07
#66
10
1B
#68
00
0B
#70
10
1B
#72
00
0B
#74
10
1B
#76
00
0B
#78
10
1B
#80
00
0B
#82
10
1B
#84
00
0B
#86
10
1B
#88
00
0B
#90
10
1B
#92
00
0B
#94
10
1B
#96
1&
00
0B
17
#98
10
1B
#100
00
0B
#102
10
1B
#104
00
0B
#106
10
1B
#108
00
0B
#110
10
1B
#112
00
0B
#114
10
1B
#116
00
0B
#118
10
1B
#120
00
0B
#122
10
1B
#124
00
0B
#126
10
1B
#128
0&
00
0B
07
#130
10
1B
#132
00
0B
#134
10
1B
#136
00
0B
#138
10
1B
#140
00
0B
#142
10
1B
#144
00
0B
#146
10
1B
#148
00
0B
#150
10
1B
#152
00
0B
#154
10
1B
#156
00
0B
#158
10
1B
#160
1&
00
0B
17
#162
10
1B
#164
00
0B
#166
10
1B
#168
00
0B
#170
10
1B
#172
00
0B
#174
10
1B
#176
00
0B
#178
10
1B
#180
00
0B
#182
10
1B
#184
00
0B
#186
10
1B
#188
00
0B
#190
10
1B
#192
0&
00
0B
07
#194
10
1B
#196
00
0B
#198
10
1B
#200
00
0B
#202
10
1B
#204
00
0B
#206
10
1B
#208
00
0B
#210
10
1B
#212
00
0B
#214
10
1B
#216
00
0B
#218
10
1B
#220
00
0B
#222
10
1B
#224
1&
00
0B
17
#226
10
1B
#228
00
0B
#230
10
1B
#232
00
0B
#234
10
1B
#236
00
0B
#238
10
1B
#240
00
0B
#242
10
1B
#244
00
0B
#246
10
1B
#248
00
0B
#250
10
1B
#252
00
0B
#254
10
1B
#256
0&
00
0B
07
#258
10
1B
#260
00
0B
#262
10
1B
#264
00
0B
#266
10
1B
#268
00
0B
#270
10
1B
#272
00
0B
#274
10
1B
#276
00
0B
#278
10
1B
#280
00
0B
#282
10
1B
#284
00
0B
#286
10
1B
#288
1&
00
0B
17
#290
10
1B
#292
00
0B
#294
10
1B
#296
00
0B
#298
10
1B
#300
00
0B
#302
10
1B
#304
00
0B
#306
10
1B
#308
00
0B
#310
10
1B
#312
00
0B
#314
10
1B
#316
00
0B
#318
10
1B
#320
0&
00
0B
07
#322
10
1B
#324
00
0B
#326
10
1B
#328
00
0B
#330
10
1B
#332
00
0B
#334
10
1B
#336
00
0B
#338
10
1B
#340
00
0B
#342
10
1B
#344
00
0B
#346
10
1B
#348
00
0B
#350
10
1B
#352
1&
00
0B
17
#354
10
1B
#356
00
0B
#358
10
1B
#360
00
0B
#362
10
1B
#364
00
0B
#366
10
1B
#368
00
0B
#370
10
1B
#372
00
0B
#374
10
1B
#376
00
0B
#378
10
1B
#380
00
0B
#382
10
1B
#384
0&
00
0B
07
#386
10
1B
#388
00
0B
#390
10
1B
#392
00
0B
#394
10
1B
#396
00
0B
#398
10
1B
#400
00
0B
#402
10
1B
#404
00
0B
#406
10
1B
#408
00
0B
#410
10
1B
#412
00
0B
#414
10
1B
#416
1&
00
0B
17
#418
10
1B
#420
00
0B
#422
10
1B
#424
00
0B
#426
10
1B
#428
00
0B
#430
10
1B
#432
00
0B
#434
10
1B
#436
00
0B
#438
10
1B
#440
00
0B
#442
10
1B
#444
00
0B
#446
10
1B
#448
0&
00
0B
07
#450
10
1B
#452
00
0B
#454
10
1B
#456
00
0B
#458
10
1B
#460
00
0B
#462
10
1B
#464
00
0B
#466
10
1B
#468
00
0B
#470
10
1B
#472
00
0B
#474
10
1B
#476
00
0B
#478
10
1B
#480
1&
00
0B
17
#482
10
1B
#484
00
0B
#486
10
1B
#488
00
0B
#490
10
1B
#492
00
0B
#494
10
1B
#496
00
0B
#498
10
1B
#500
b0 .
00
0B
#502
10
1B
#504
00
0B
#506
10
1B
#508
00
0B
#510
10
1B
#512
0&
00
0B
07
#514
10
1B
#516
00
0B
#518
10
1B
#520
00
0B
#522
10
1B
#524
00
0B
#526
10
1B
#528
00
0B
#530
10
1B
#532
00
0B
#534
10
1B
#536
00
0B
#538
10
1B
#540
00
0B
#542
10
1B
#544
1&
00
1%
b0 -
0B
17
#546
10
1B
#548
00
0B
#550
10
1B
#552
00
0B
#554
10
1B
#556
00
0B
#558
10
1B
#560
00
0B
#562
10
1B
#564
00
0B
#566
10
1B
#568
00
0B
#570
10
1B
#572
00
0B
#574
10
1B
#576
0&
00
0B
07
#578
10
1B
#580
00
0B
#582
10
1B
#584
00
0B
#586
10
1B
#588
00
0B
#590
10
1B
#592
00
0B
#594
10
1B
#596
00
0B
#598
10
1B
#600
00
0B
#602
10
1B
#604
00
0B
#606
10
1B
#608
1&
00
0%
0B
17
#610
10
1B
#612
00
0B
#614
10
1B
#616
00
0B
#618
10
1B
#620
00
0B
#622
10
1B
#624
00
0B
#626
10
1B
#628
00
0B
#630
10
1B
#632
00
0B
#634
10
1B
#636
00
0B
#638
10
1B
#640
0&
00
0B
07
#642
10
1B
#644
00
0B
#646
10
1B
#648
00
0B
#650
10
1B
#652
00
0B
#654
10
1B
#656
00
0B
#658
10
1B
#660
00
0B
#662
10
1B
#664
00
0B
#666
10
1B
#668
00
0B
#670
10
1B
#672
1&
00
b10100011110110001110011011011011 !
b1000111 (
b1000111 9
0B
17
#674
10
1B
#676
00
0B
#678
10
1B
#680
00
0B
#682
10
1B
#684
00
0B
#686
10
1B
#688
00
0B
#690
10
1B
#692
00
0B
#694
10
1B
#696
00
0B
#698
10
1B
#700
00
0B
#702
10
1B
#704
0&
00
0B
07
#706
10
1B
#708
00
0B
#710
10
1B
#712
00
0B
#714
10
1B
#716
00
0B
#718
10
1B
#720
00
0B
#722
10
1B
#724
00
0B
#726
10
1B
#728
00
0B
#730
10
1B
#732
00
0B
#734
10
1B
#736
1&
00
1'
1)
1:
18
0B
13
17
b1000111 =
0<
0+
#738
10
1B
#740
00
0B
#742
10
1B
#744
00
0B
#746
10
1B
#748
00
0B
#750
10
1B
#752
00
0B
#754
10
1B
#756
00
0B
#758
10
1B
#760
00
0B
#762
10
1B
#764
00
0B
#766
10
1B
#768
0&
00
0B
07
#770
10
1B
#772
00
0B
#774
10
1B
#776
00
0B
#778
10
1B
#780
00
0B
#782
10
1B
#784
00
0B
#786
10
1B
#788
00
0B
#790
10
1B
#792
00
0B
#794
10
1B
#796
00
0B
#798
10
1B
#800
1&
00
0'
b0 "
08
0B
17
0;
b1 ?
0*
04
#802
10
1B
0K
#804
00
0B
#806
10
1B
0L
#808
00
0B
#810
10
1B
1M
b1 G
b0 H
#812
00
0B
#814
10
1B
b10 G
#816
00
0B
#818
10
1B
b11 G
#820
00
0B
#822
10
1B
b100 G
#824
00
0B
#826
10
1B
b101 G
#828
00
0B
#830
10
1B
b110 G
#832
0&
00
0B
07
#834
10
1B
b111 G
#836
00
0B
#838
10
1B
b1000 G
b1 H
#840
00
0B
#842
10
1B
b1001 G
#844
00
0B
#846
10
1B
b1010 G
#848
00
0B
#850
10
1B
b1011 G
#852
00
0B
#854
10
1B
b1100 G
#856
00
0B
#858
10
1B
b1101 G
#860
00
0B
#862
10
1B
b1110 G
#864
1&
00
b1 "
b1 -
0B
17
1;
b10 ?
1*
14
#866
10
1B
1K
b1111 G
#868
00
0B
#870
10
1B
1L
b0 G
#872
00
0B
#874
10
1B
b1 G
#876
00
0B
#878
10
1B
b10 G
#880
00
0B
#882
10
1B
b11 G
#884
00
0B
#886
10
1B
b100 G
#888
00
0B
#890
10
1B
b101 G
#892
00
0B
#894
10
1B
b110 G
#896
0&
00
0B
07
#898
10
1B
b111 G
#900
00
0B
#902
10
1B
b1000 G
b10 H
bx1 F
#904
00
0B
#906
10
1B
b1001 G
#908
00
0B
#910
10
1B
b1010 G
#912
00
0B
#914
10
1B
b1011 G
#916
00
0B
#918
10
1B
b1100 G
#920
00
0B
#922
10
1B
b1101 G
#924
00
0B
#926
10
1B
b1110 G
#928
1&
00
b10 ,
b10 -
b10 "
0B
17
b11 ?
#930
10
1B
b1111 G
#932
00
0B
#934
10
1B
b0 G
#936
00
0B
#938
10
1B
b1 G
#940
00
0B
#942
10
1B
b10 G
#944
00
0B
#946
10
1B
b11 G
#948
00
0B
#950
10
1B
b100 G
#952
00
0B
#954
10
1B
b101 G
#956
00
0B
#958
10
1B
b110 G
#960
0&
00
0B
07
#962
10
1B
b111 G
#964
00
0B
#966
10
1B
b1000 G
b11 H
bx11 F
#968
00
0B
#970
10
1B
b1001 G
#972
00
0B
#974
10
1B
b1010 G
#976
00
0B
#978
10
1B
b1011 G
#980
00
0B
#982
10
1B
b1100 G
#984
00
0B
#986
10
1B
b1101 G
#988
00
0B
#990
10
1B
b1110 G
#992
1&
00
b110 ,
b11 -
b11 "
0B
17
b100 ?
#994
10
1B
b1111 G
#996
00
0B
#998
10
1B
b0 G
#1000
00
0B
#1002
10
1B
b1 G
#1004
00
0B
#1006
10
1B
b10 G
#1008
00
0B
#1010
10
1B
b11 G
#1012
00
0B
#1014
10
1B
b100 G
#1016
00
0B
#1018
10
1B
b101 G
#1020
00
0B
#1022
10
1B
b110 G
#1024
0&
00
0B
07
#1026
10
1B
b111 G
#1028
00
0B
#1030
10
1B
b1000 G
b100 H
bx111 F
#1032
00
0B
#1034
10
1B
b1001 G
#1036
00
0B
#1038
10
1B
b1010 G
#1040
00
0B
#1042
10
1B
b1011 G
#1044
00
0B
#1046
10
1B
b1100 G
#1048
00
0B
#1050
10
1B
b1101 G
#1052
00
0B
#1054
10
1B
b1110 G
#1056
1&
00
b1110 ,
b100 -
b100 "
0B
17
0;
b101 ?
0*
04
#1058
10
1B
0K
b1111 G
#1060
00
0B
#1062
10
1B
0L
b0 G
#1064
00
0B
#1066
10
1B
b1 G
#1068
00
0B
#1070
10
1B
b10 G
#1072
00
0B
#1074
10
1B
b11 G
#1076
00
0B
#1078
10
1B
b100 G
#1080
00
0B
#1082
10
1B
b101 G
#1084
00
0B
#1086
10
1B
b110 G
#1088
0&
00
0B
07
#1090
10
1B
b111 G
#1092
00
0B
#1094
10
1B
b1000 G
b101 H
bx0111 F
#1096
00
0B
#1098
10
1B
b1001 G
#1100
00
0B
#1102
10
1B
b1010 G
#1104
00
0B
#1106
10
1B
b1011 G
#1108
00
0B
#1110
10
1B
b1100 G
#1112
00
0B
#1114
10
1B
b1101 G
#1116
00
0B
#1118
10
1B
b1110 G
#1120
1&
00
b101 -
b101 "
0B
17
b110 ?
#1122
10
1B
b1111 G
#1124
00
0B
#1126
10
1B
b0 G
#1128
00
0B
#1130
10
1B
b1 G
#1132
00
0B
#1134
10
1B
b10 G
#1136
00
0B
#1138
10
1B
b11 G
#1140
00
0B
#1142
10
1B
b100 G
#1144
00
0B
#1146
10
1B
b101 G
#1148
00
0B
#1150
10
1B
b110 G
#1152
0&
00
0B
07
#1154
10
1B
b111 G
#1156
00
0B
#1158
10
1B
b1000 G
b110 H
bx00111 F
#1160
00
0B
#1162
10
1B
b1001 G
#1164
00
0B
#1166
10
1B
b1010 G
#1168
00
0B
#1170
10
1B
b1011 G
#1172
00
0B
#1174
10
1B
b1100 G
#1176
00
0B
#1178
10
1B
b1101 G
#1180
00
0B
#1182
10
1B
b1110 G
#1184
1&
00
b110 -
b110 "
0B
17
b111 ?
#1186
10
1B
b1111 G
#1188
00
0B
#1190
10
1B
b0 G
#1192
00
0B
#1194
10
1B
b1 G
#1196
00
0B
#1198
10
1B
b10 G
#1200
00
0B
#1202
10
1B
b11 G
#1204
00
0B
#1206
10
1B
b100 G
#1208
00
0B
#1210
10
1B
b101 G
#1212
00
0B
#1214
10
1B
b110 G
#1216
0&
00
0B
07
#1218
10
1B
b111 G
#1220
00
0B
#1222
10
1B
b1000 G
b111 H
bx000111 F
#1224
00
0B
#1226
10
1B
b1001 G
#1228
00
0B
#1230
10
1B
b1010 G
#1232
00
0B
#1234
10
1B
b1011 G
#1236
00
0B
#1238
10
1B
b1100 G
#1240
00
0B
#1242
10
1B
b1101 G
#1244
00
0B
#1246
10
1B
b1110 G
#1248
1&
00
b111 -
b111 "
0B
17
1;
b1000 ?
1*
14
#1250
10
1B
1K
b1111 G
#1252
00
0B
#1254
10
1B
1L
b0 G
#1256
00
0B
#1258
10
1B
b1 G
#1260
00
0B
#1262
10
1B
b10 G
#1264
00
0B
#1266
10
1B
b11 G
#1268
00
0B
#1270
10
1B
b100 G
#1272
00
0B
#1274
10
1B
b101 G
#1276
00
0B
#1278
10
1B
b110 G
#1280
0&
00
0B
07
#1282
10
1B
b111 G
#1284
00
0B
#1286
10
1B
b1000 G
b1000 H
bx1000111 F
#1288
00
0B
#1290
10
1B
b1001 G
#1292
00
0B
#1294
10
1B
b1010 G
#1296
00
0B
#1298
10
1B
b1011 G
#1300
00
0B
#1302
10
1B
b1100 G
#1304
00
0B
#1306
10
1B
b1101 G
#1308
00
0B
#1310
10
1B
b1110 G
#1312
1&
00
b10001110 ,
b1000 -
b1000 "
0B
17
0;
b1001 ?
0*
04
#1314
10
1B
0K
b1111 G
#1316
00
0B
#1318
10
1B
0L
b0 G
#1320
00
0B
#1322
10
1B
b1 G
#1324
00
0B
#1326
10
1B
b10 G
#1328
00
0B
#1330
10
1B
b11 G
#1332
00
0B
#1334
10
1B
b100 G
#1336
00
0B
#1338
10
1B
b101 G
#1340
00
0B
#1342
10
1B
b110 G
#1344
0&
00
0B
07
#1346
10
1B
b111 G
#1348
00
0B
#1350
10
1B
b1000 G
b1001 H
b1000111 F
#1352
00
0B
#1354
10
1B
b1001 G
#1356
00
0B
#1358
10
1B
b1010 G
#1360
00
0B
#1362
10
1B
b1011 G
#1364
00
0B
#1366
10
1B
b1100 G
#1368
00
0B
#1370
10
1B
b1101 G
#1372
00
0B
#1374
10
1B
b1110 G
#1376
1&
00
b1001 -
b1001 "
0B
17
1;
b1010 ?
1<
1+
1*
14
#1378
10
1B
1K
b1111 G
#1380
00
0B
#1382
10
1B
1L
b0 G
#1384
00
0B
#1386
10
1B
b1 G
#1388
00
0B
#1390
10
1B
b10 G
#1392
00
0B
#1394
10
1B
b11 G
#1396
00
0B
#1398
10
1B
b100 G
#1400
00
0B
#1402
10
1B
b101 G
#1404
00
0B
#1406
10
1B
b110 G
#1408
0&
00
0B
07
#1410
10
1B
b111 G
#1412
00
0B
#1414
10
1B
b1000 G
b1010 H
0M
0E
0I
05
#1416
00
0B
#1418
10
11
1C
1B
b1000111 D
1E
15
b1000111 2
#1420
00
0B
#1422
10
01
0C
1B
#1424
00
0B
#1426
10
1B
#1428
00
0B
#1430
10
1B
#1432
00
0B
#1434
10
1B
#1436
00
0B
#1438
10
1B
#1440
1&
00
b1010001110 ,
b1010 -
0)
b0 "
0:
0B
03
17
b0 ?
#1442
10
1B
#1444
00
0B
#1446
10
1B
#1448
00
0B
#1450
10
1B
#1452
00
0B
#1454
10
1B
#1456
00
0B
#1458
10
1B
#1460
00
0B
#1462
10
1B
#1464
00
0B
#1466
10
1B
#1468
00
0B
#1470
10
1B
#1472
0&
00
0B
07
#1474
10
1B
#1476
00
0B
#1478
10
1B
#1480
00
0B
#1482
10
1B
#1484
00
0B
#1486
10
1B
#1488
00
0B
#1490
10
1B
#1492
00
0B
#1494
10
1B
#1496
00
0B
#1498
10
1B
#1500
00
0B
#1502
10
1B
#1504
1&
00
b1011 -
b1 #
b1 $
b1 "
0B
17
#1506
10
1B
#1508
00
0B
#1510
10
1B
#1512
00
0B
#1514
10
1B
#1516
00
0B
#1518
10
1B
#1520
00
0B
#1522
10
1B
#1524
00
0B
#1526
10
1B
#1528
00
0B
#1530
10
1B
#1532
00
0B
#1534
10
1B
#1536
0&
00
0B
07
#1538
10
1B
#1540
00
0B
#1542
10
1B
#1544
00
0B
#1546
10
1B
#1548
00
0B
#1550
10
1B
#1552
00
0B
#1554
10
1B
#1556
00
0B
#1558
10
1B
#1560
00
0B
#1562
10
1B
#1564
00
0B
#1566
10
1B
#1568
1&
00
b10 "
0B
17
#1570
10
1B
#1572
00
0B
#1574
10
1B
#1576
00
0B
#1578
10
1B
#1580
00
0B
#1582
10
1B
#1584
00
0B
#1586
10
1B
#1588
00
0B
#1590
10
1B
#1592
00
0B
#1594
10
1B
#1596
00
0B
#1598
10
1B
#1600
0&
00
0B
07
#1602
10
1B
#1604
00
0B
#1606
10
1B
#1608
00
0B
#1610
10
1B
#1612
00
0B
#1614
10
1B
#1616
00
0B
#1618
10
1B
#1620
00
0B
#1622
10
1B
#1624
00
0B
#1626
10
1B
#1628
00
0B
#1630
10
1B
#1632
1&
00
b11 "
0B
17
#1634
10
1B
#1636
00
0B
#1638
10
1B
#1640
00
0B
#1642
10
1B
#1644
00
0B
#1646
10
1B
#1648
00
0B
#1650
10
1B
#1652
00
0B
#1654
10
1B
#1656
00
0B
#1658
10
1B
#1660
00
0B
#1662
10
1B
#1664
0&
00
0B
07
#1666
10
1B
#1668
00
0B
#1670
10
1B
#1672
00
0B
#1674
10
1B
#1676
00
0B
#1678
10
1B
#1680
00
0B
#1682
10
1B
#1684
00
0B
#1686
10
1B
#1688
00
0B
#1690
10
1B
#1692
00
0B
#1694
10
1B
#1696
1&
00
b100 "
0B
17
#1698
10
1B
#1700
00
0B
#1702
10
1B
#1704
00
0B
#1706
10
1B
#1708
00
0B
#1710
10
1B
#1712
00
0B
#1714
10
1B
#1716
00
0B
#1718
10
1B
#1720
00
0B
#1722
10
1B
#1724
00
0B
#1726
10
1B
#1728
0&
00
0B
07
#1730
10
1B
#1732
00
0B
#1734
10
1B
#1736
00
0B
#1738
10
1B
#1740
00
0B
#1742
10
1B
#1744
00
0B
#1746
10
1B
#1748
00
0B
#1750
10
1B
#1752
00
0B
#1754
10
1B
#1756
00
0B
#1758
10
1B
#1760
1&
00
b101 "
0B
17
#1762
10
1B
#1764
00
0B
#1766
10
1B
#1768
00
0B
#1770
10
1B
#1772
00
0B
#1774
10
1B
#1776
00
0B
#1778
10
1B
#1780
00
0B
#1782
10
1B
#1784
00
0B
#1786
10
1B
#1788
00
0B
#1790
10
1B
#1792
0&
00
0B
07
#1794
10
1B
#1796
00
0B
#1798
10
1B
#1800
00
0B
#1802
10
1B
#1804
00
0B
#1806
10
1B
#1808
00
0B
#1810
10
1B
#1812
00
0B
#1814
10
1B
#1816
00
0B
#1818
10
1B
#1820
00
0B
#1822
10
1B
#1824
1&
00
b110 "
0B
17
#1826
10
1B
#1828
00
0B
#1830
10
1B
#1832
00
0B
#1834
10
1B
#1836
00
0B
#1838
10
1B
#1840
00
0B
#1842
10
1B
#1844
00
0B
#1846
10
1B
#1848
00
0B
#1850
10
1B
#1852
00
0B
#1854
10
1B
#1856
0&
00
0B
07
#1858
10
1B
#1860
00
0B
#1862
10
1B
#1864
00
0B
#1866
10
1B
#1868
00
0B
#1870
10
1B
#1872
00
0B
#1874
10
1B
#1876
00
0B
#1878
10
1B
#1880
00
0B
#1882
10
1B
#1884
00
0B
#1886
10
1B
#1888
1&
00
b111 "
0B
17
